odoo/addons/web_ir_actions_act_view_reload/README.rst
odoo/addons/web_ir_actions_act_view_reload/__init__.py
odoo/addons/web_ir_actions_act_view_reload/__manifest__.py
odoo/addons/web_ir_actions_act_view_reload/i18n/web_ir_actions_act_view_reload.pot
odoo/addons/web_ir_actions_act_view_reload/i18n/zh_CN.po
odoo/addons/web_ir_actions_act_view_reload/models/__init__.py
odoo/addons/web_ir_actions_act_view_reload/models/ir_actions_act_view_reload.py
odoo/addons/web_ir_actions_act_view_reload/readme/CONTRIBUTORS.rst
odoo/addons/web_ir_actions_act_view_reload/readme/DESCRIPTION.rst
odoo/addons/web_ir_actions_act_view_reload/readme/USAGE.rst
odoo/addons/web_ir_actions_act_view_reload/static/description/icon.png
odoo/addons/web_ir_actions_act_view_reload/static/description/index.html
odoo/addons/web_ir_actions_act_view_reload/static/src/js/web_ir_actions_act_view_reload.esm.js
odoo_addon_web_ir_actions_act_view_reload-15.0.1.0.1.1.dist-info/METADATA
odoo_addon_web_ir_actions_act_view_reload-15.0.1.0.1.1.dist-info/WHEEL
odoo_addon_web_ir_actions_act_view_reload-15.0.1.0.1.1.dist-info/top_level.txt
odoo_addon_web_ir_actions_act_view_reload-15.0.1.0.1.1.dist-info/RECORD
